capybaradb/__init__.py
capybaradb/_client.py
capybaradb/_collection.py
capybaradb/_database.py
capybaradb/_emb_json/__init__.py
capybaradb/_emb_json/_emb_image.py
capybaradb/_emb_json/_emb_models.py
capybaradb/_emb_json/_emb_text.py
capybaradb/_emb_json/_vision_models.py
capybaradb/_types.py
capybaradb-0.2.8.dist-info/LICENSE
capybaradb-0.2.8.dist-info/METADATA
capybaradb-0.2.8.dist-info/WHEEL
capybaradb-0.2.8.dist-info/RECORD
