Metadata-Version: 2.3
Name: capybaradb
Version: 0.2.8
Summary: 
License: Apache-2.0
Author: CapybaraDB
Requires-Python: >=3.8,<4.0
Classifier: License :: OSI Approved :: Apache Software License
Classifier: Programming Language :: Python :: 3
Classifier: Programming Language :: Python :: 3.8
Classifier: Programming Language :: Python :: 3.9
Classifier: Programming Language :: Python :: 3.10
Classifier: Programming Language :: Python :: 3.11
Classifier: Programming Language :: Python :: 3.12
Classifier: Programming Language :: Python :: 3.13
Requires-Dist: pymongo (>=4.10.1,<5.0.0)
Requires-Dist: requests (>=2.32.3,<3.0.0)
